openapi_ts/__init__.py
openapi_ts/main.py
openapi_ts-0.1.4.dist-info/METADATA
openapi_ts-0.1.4.dist-info/WHEEL
openapi_ts-0.1.4.dist-info/top_level.txt
openapi_ts-0.1.4.dist-info/RECORD
