Metadata-Version: 2.1
Name: openapi-ts
Version: 0.1.4
Summary: Generate typescript clients for OpenAPI (e.g. FastAPI) apps, using openapi-ts
Author-email: Marcel Claramunt <marcel@moveread.com>
Project-URL: repo, https://github.com/moveread/REPO.git
Requires-Python: >=3.10
